{"version":"1.0","encoding":"UTF-8","feed":{"xmlns":"http://www.w3.org/2005/Atom","xmlns$openSearch":"http://a9.com/-/spec/opensearchrss/1.0/","xmlns$gsx":"http://schemas.google.com/spreadsheets/2006/extended","id":{"$t":"https://spreadsheets.google.com/feeds/list/1XPmeY6xjK4VGTGxjff_NrPkpzwKk3U0x6p90cqg09dc/od6/public/values"},"updated":{"$t":"2019-02-08T01:59:05.978Z"},"category":[{"scheme":"http://schemas.google.com/spreadsheets/2006","term":"http://schemas.google.com/spreadsheets/2006#list"}],"title":{"type":"text","$t":"Hoja 1"},"link":[{"rel":"alternate","type":"application/atom+xml","href":"https://docs.google.com/spreadsheets/d/1XPmeY6xjK4VGTGxjff_NrPkpzwKk3U0x6p90cqg09dc/pubhtml"},{"rel":"http://schemas.google.com/g/2005#feed","type":"application/atom+xml","href":"https://spreadsheets.google.com/feeds/list/1XPmeY6xjK4VGTGxjff_NrPkpzwKk3U0x6p90cqg09dc/od6/public/values"},{"rel":"http://schemas.google.com/g/2005#post","type":"application/atom+xml","href":"https://spreadsheets.google.com/feeds/list/1XPmeY6xjK4VGTGxjff_NrPkpzwKk3U0x6p90cqg09dc/od6/public/values"},{"rel":"self","type":"application/atom+xml","href":"https://spreadsheets.google.com/feeds/list/1XPmeY6xjK4VGTGxjff_NrPkpzwKk3U0x6p90cqg09dc/od6/public/values?alt\u003djson"}],"author":[{"name":{"$t":"scharss"},"email":{"$t":"scharss@gmail.com"}}],"openSearch$totalResults":{"$t":"11"},"openSearch$startIndex":{"$t":"1"},"entry":[{"id":{"$t":"https://spreadsheets.google.com/feeds/list/1XPmeY6xjK4VGTGxjff_NrPkpzwKk3U0x6p90cqg09dc/od6/public/values/cokwr"},"updated":{"$t":"2019-02-08T01:59:05.978Z"},"category":[{"scheme":"http://schemas.google.com/spreadsheets/2006","term":"http://schemas.google.com/spreadsheets/2006#list"}],"title":{"type":"text","$t":"A"},"content":{"type":"text","$t":"age: 12, sub2: ERER, tag: DFDDS"},"link":[{"rel":"self","type":"application/atom+xml","href":"https://spreadsheets.google.com/feeds/list/1XPmeY6xjK4VGTGxjff_NrPkpzwKk3U0x6p90cqg09dc/od6/public/values/cokwr"}],"gsx$name":{"$t":"A"},"gsx$age":{"$t":"12"},"gsx$sub2":{"$t":"ERER"},"gsx$tag":{"$t":"DFDDS"}},{"id":{"$t":"https://spreadsheets.google.com/feeds/list/1XPmeY6xjK4VGTGxjff_NrPkpzwKk3U0x6p90cqg09dc/od6/public/values/cpzh4"},"updated":{"$t":"2019-02-08T01:59:05.978Z"},"category":[{"scheme":"http://schemas.google.com/spreadsheets/2006","term":"http://schemas.google.com/spreadsheets/2006#list"}],"title":{"type":"text","$t":"A"},"content":{"type":"text","$t":"age: 23, sub2: SDASDFDS, tag: FDDSFD"},"link":[{"rel":"self","type":"application/atom+xml","href":"https://spreadsheets.google.com/feeds/list/1XPmeY6xjK4VGTGxjff_NrPkpzwKk3U0x6p90cqg09dc/od6/public/values/cpzh4"}],"gsx$name":{"$t":"A"},"gsx$age":{"$t":"23"},"gsx$sub2":{"$t":"SDASDFDS"},"gsx$tag":{"$t":"FDDSFD"}},{"id":{"$t":"https://spreadsheets.google.com/feeds/list/1XPmeY6xjK4VGTGxjff_NrPkpzwKk3U0x6p90cqg09dc/od6/public/values/cre1l"},"updated":{"$t":"2019-02-08T01:59:05.978Z"},"category":[{"scheme":"http://schemas.google.com/spreadsheets/2006","term":"http://schemas.google.com/spreadsheets/2006#list"}],"title":{"type":"text","$t":"A"},"content":{"type":"text","$t":"age: 4, sub2: DFD, tag: VCXCZXC"},"link":[{"rel":"self","type":"application/atom+xml","href":"https://spreadsheets.google.com/feeds/list/1XPmeY6xjK4VGTGxjff_NrPkpzwKk3U0x6p90cqg09dc/od6/public/values/cre1l"}],"gsx$name":{"$t":"A"},"gsx$age":{"$t":"4"},"gsx$sub2":{"$t":"DFD"},"gsx$tag":{"$t":"VCXCZXC"}},{"id":{"$t":"https://spreadsheets.google.com/feeds/list/1XPmeY6xjK4VGTGxjff_NrPkpzwKk3U0x6p90cqg09dc/od6/public/values/chk2m"},"updated":{"$t":"2019-02-08T01:59:05.978Z"},"category":[{"scheme":"http://schemas.google.com/spreadsheets/2006","term":"http://schemas.google.com/spreadsheets/2006#list"}],"title":{"type":"text","$t":"A"},"content":{"type":"text","$t":"age: 5, sub2: DFDSDS, tag: EDAEE"},"link":[{"rel":"self","type":"application/atom+xml","href":"https://spreadsheets.google.com/feeds/list/1XPmeY6xjK4VGTGxjff_NrPkpzwKk3U0x6p90cqg09dc/od6/public/values/chk2m"}],"gsx$name":{"$t":"A"},"gsx$age":{"$t":"5"},"gsx$sub2":{"$t":"DFDSDS"},"gsx$tag":{"$t":"EDAEE"}},{"id":{"$t":"https://spreadsheets.google.com/feeds/list/1XPmeY6xjK4VGTGxjff_NrPkpzwKk3U0x6p90cqg09dc/od6/public/values/ciyn3"},"updated":{"$t":"2019-02-08T01:59:05.978Z"},"category":[{"scheme":"http://schemas.google.com/spreadsheets/2006","term":"http://schemas.google.com/spreadsheets/2006#list"}],"title":{"type":"text","$t":"B"},"content":{"type":"text","$t":"age: 3, sub2: DDFD, tag: CXVDX"},"link":[{"rel":"self","type":"application/atom+xml","href":"https://spreadsheets.google.com/feeds/list/1XPmeY6xjK4VGTGxjff_NrPkpzwKk3U0x6p90cqg09dc/od6/public/values/ciyn3"}],"gsx$name":{"$t":"B"},"gsx$age":{"$t":"3"},"gsx$sub2":{"$t":"DDFD"},"gsx$tag":{"$t":"CXVDX"}},{"id":{"$t":"https://spreadsheets.google.com/feeds/list/1XPmeY6xjK4VGTGxjff_NrPkpzwKk3U0x6p90cqg09dc/od6/public/values/ckd7g"},"updated":{"$t":"2019-02-08T01:59:05.978Z"},"category":[{"scheme":"http://schemas.google.com/spreadsheets/2006","term":"http://schemas.google.com/spreadsheets/2006#list"}],"title":{"type":"text","$t":"B"},"content":{"type":"text","$t":"age: 4, sub2: DVCX, tag: DFDS"},"link":[{"rel":"self","type":"application/atom+xml","href":"https://spreadsheets.google.com/feeds/list/1XPmeY6xjK4VGTGxjff_NrPkpzwKk3U0x6p90cqg09dc/od6/public/values/ckd7g"}],"gsx$name":{"$t":"B"},"gsx$age":{"$t":"4"},"gsx$sub2":{"$t":"DVCX"},"gsx$tag":{"$t":"DFDS"}},{"id":{"$t":"https://spreadsheets.google.com/feeds/list/1XPmeY6xjK4VGTGxjff_NrPkpzwKk3U0x6p90cqg09dc/od6/public/values/clrrx"},"updated":{"$t":"2019-02-08T01:59:05.978Z"},"category":[{"scheme":"http://schemas.google.com/spreadsheets/2006","term":"http://schemas.google.com/spreadsheets/2006#list"}],"title":{"type":"text","$t":"B"},"content":{"type":"text","$t":"age: 6, sub2: CV, tag: VCXZ"},"link":[{"rel":"self","type":"application/atom+xml","href":"https://spreadsheets.google.com/feeds/list/1XPmeY6xjK4VGTGxjff_NrPkpzwKk3U0x6p90cqg09dc/od6/public/values/clrrx"}],"gsx$name":{"$t":"B"},"gsx$age":{"$t":"6"},"gsx$sub2":{"$t":"CV"},"gsx$tag":{"$t":"VCXZ"}},{"id":{"$t":"https://spreadsheets.google.com/feeds/list/1XPmeY6xjK4VGTGxjff_NrPkpzwKk3U0x6p90cqg09dc/od6/public/values/cyevm"},"updated":{"$t":"2019-02-08T01:59:05.978Z"},"category":[{"scheme":"http://schemas.google.com/spreadsheets/2006","term":"http://schemas.google.com/spreadsheets/2006#list"}],"title":{"type":"text","$t":"B"},"content":{"type":"text","$t":"age: 6, sub2: CVXCX, tag: REER"},"link":[{"rel":"self","type":"application/atom+xml","href":"https://spreadsheets.google.com/feeds/list/1XPmeY6xjK4VGTGxjff_NrPkpzwKk3U0x6p90cqg09dc/od6/public/values/cyevm"}],"gsx$name":{"$t":"B"},"gsx$age":{"$t":"6"},"gsx$sub2":{"$t":"CVXCX"},"gsx$tag":{"$t":"REER"}},{"id":{"$t":"https://spreadsheets.google.com/feeds/list/1XPmeY6xjK4VGTGxjff_NrPkpzwKk3U0x6p90cqg09dc/od6/public/values/cztg3"},"updated":{"$t":"2019-02-08T01:59:05.978Z"},"category":[{"scheme":"http://schemas.google.com/spreadsheets/2006","term":"http://schemas.google.com/spreadsheets/2006#list"}],"title":{"type":"text","$t":"C"},"content":{"type":"text","$t":"age: 77, sub2: CXV, tag: BCFC"},"link":[{"rel":"self","type":"application/atom+xml","href":"https://spreadsheets.google.com/feeds/list/1XPmeY6xjK4VGTGxjff_NrPkpzwKk3U0x6p90cqg09dc/od6/public/values/cztg3"}],"gsx$name":{"$t":"C"},"gsx$age":{"$t":"77"},"gsx$sub2":{"$t":"CXV"},"gsx$tag":{"$t":"BCFC"}},{"id":{"$t":"https://spreadsheets.google.com/feeds/list/1XPmeY6xjK4VGTGxjff_NrPkpzwKk3U0x6p90cqg09dc/od6/public/values/d180g"},"updated":{"$t":"2019-02-08T01:59:05.978Z"},"category":[{"scheme":"http://schemas.google.com/spreadsheets/2006","term":"http://schemas.google.com/spreadsheets/2006#list"}],"title":{"type":"text","$t":"C"},"content":{"type":"text","$t":"age: 8, sub2: CXV, tag: XC"},"link":[{"rel":"self","type":"application/atom+xml","href":"https://spreadsheets.google.com/feeds/list/1XPmeY6xjK4VGTGxjff_NrPkpzwKk3U0x6p90cqg09dc/od6/public/values/d180g"}],"gsx$name":{"$t":"C"},"gsx$age":{"$t":"8"},"gsx$sub2":{"$t":"CXV"},"gsx$tag":{"$t":"XC"}},{"id":{"$t":"https://spreadsheets.google.com/feeds/list/1XPmeY6xjK4VGTGxjff_NrPkpzwKk3U0x6p90cqg09dc/od6/public/values/d2mkx"},"updated":{"$t":"2019-02-08T01:59:05.978Z"},"category":[{"scheme":"http://schemas.google.com/spreadsheets/2006","term":"http://schemas.google.com/spreadsheets/2006#list"}],"title":{"type":"text","$t":"C"},"content":{"type":"text","$t":"age: 7, sub2: RRGE, tag: CCX"},"link":[{"rel":"self","type":"application/atom+xml","href":"https://spreadsheets.google.com/feeds/list/1XPmeY6xjK4VGTGxjff_NrPkpzwKk3U0x6p90cqg09dc/od6/public/values/d2mkx"}],"gsx$name":{"$t":"C"},"gsx$age":{"$t":"7"},"gsx$sub2":{"$t":"RRGE"},"gsx$tag":{"$t":"CCX"}}]}}